ROTools/__init__.py
ROTools/Config/Config.py
ROTools/Config/ConfigLoader.py
ROTools/Config/__init__.py
ROTools/Helpers/Attr.py
ROTools/Helpers/CoordinatesGPS.py
ROTools/Helpers/RedisSingletonLock.py
ROTools/Helpers/RequestHelper.py
ROTools/Helpers/SignalHandler.py
ROTools/Helpers/StopWatch.py
ROTools/Helpers/WorkersCollection.py
ROTools/Helpers/__init__.py
ROTools/Helpers/db_helpers.py
ROTools/Helpers/df_helpers.py
ROTools/Helpers/flask_helpers.py
ROTools/Helpers/log_helpers.py
ROTools/Helpers/marshmallow_helpers.py
ROTools/Helpers/text_helpers.py
ROTools/Helpers/time_helpers.py
ROTools/Wrappers/MinioWrapper.py
ROTools/Wrappers/PathWrapper.py
ROTools/Wrappers/SFTPWrapper.py
ROTools/Wrappers/__init__.py
ROTools/core/DictObj.py
ROTools/core/DumpBase.py
ROTools/core/HashBuilder.py
ROTools/core/RateLimiter.py
ROTools/core/SleepController.py
ROTools/core/SmartCounter.py
ROTools/core/StringBuilder.py
ROTools/core/__init__.py
ROTools/dao/BaseDao.py
ROTools/dao/LastTimeDao.py
ROTools/dao/TaskDao.py
ROTools/dao/__init__.py
ROTools/logs/ShortNameFilter.py
ROTools/logs/StatusCodesFilter.py
ROTools/logs/__init__.py
rotools-0.1.161.dist-info/licenses/LICENSE
rotools-0.1.161.dist-info/METADATA
rotools-0.1.161.dist-info/WHEEL
rotools-0.1.161.dist-info/top_level.txt
rotools-0.1.161.dist-info/RECORD
