Metadata-Version: 2.4
Name: rotools
Version: 0.1.161
Summary: Robert Olechowski python tools
Home-page: https://github.com/RobertOlechowski/ROTools
Author: Robert Olechowski
Author-email: robertolechowski@gmail.com
Requires-Python: >=3.13
License-File: LICENSE
Requires-Dist: PyYAML>=6.0.3
Requires-Dist: humanize>=4.14.0
Dynamic: author
Dynamic: author-email
Dynamic: description
Dynamic: description-content-type
Dynamic: home-page
Dynamic: license-file
Dynamic: requires-dist
Dynamic: requires-python
Dynamic: summary
